{
	"tenant_based_services": ["3DSpace","3DSearch","6WTags"],
	"act_open_item": "open_item",
	"act_open_verexpl": "open_verexpl",
	"id_logicalref": "logical_ref",
	"id_functionalref": "functional_ref",
	"attr_title": "Title",
	"attr_VName": "PLMEntity.V_Name",
    "rel_specification": "SpecificationDocument",
	"rel_document": "PLMDocConnection",
	"rel_logicalInstance":"Logical Instance",
	"contentType_instance": "instance",
	"contentType_document": "document",
	"contentType_representation": "representation",
	"contentType_link": "link",
	"type_spaceRoot": "SPP_SpaceConceptRoot",
	"type_model": "Model",
	"type_document": "Document",
  "type_documents": "Documents",
	"type_products": "Products",
	"types_addExistingDoc": "Document,Quality System Document,Technical Document",
	"type_modelVersion": "Hardware Product",
	"type_productConfiguration": "Product Configuration",
	"type_logicalref": "Logical Reference",
	"type_functionalref": "Functional Reference",
	"type_logicalrep": "Logical Representation Reference",
	"type_functionalrep": "Functional Representation Reference",
	"type_act_functref": "RFLPLMFunctionalReference",
	"type_act_logref": "RFLVPMLogicalReference",
	"type_act_functrepref": "RFLPLMFunctionalRepReference",
	"type_act_logrepref": "RFLVPMLogicalRepReference",
	"type_usecase": "Use Case",
	"type_requirement": "Requirement",
	"type_chapter": "Chapter",
	"type_reqSpec": "Requirement Specification",
	"type_reqGroup": "Requirement Group",
	"type_act_loginstance": "RFLVPMLogicalInstance",
	"type_act_physical": "VPMReference",
	"type_act_advfilter": "ENOStrRefinementSpecification",
    "type_space_concept_node": "SPP_SpaceConceptNode",
	"type_design_ref": "SSM_DesignSpaceRef",
	"type_attach_document": "attachedDocumentsCategory",
	"type_spec_document": "specificationDocumentsCategory",
	"type_proposed_solution": "proposedSolutionCategory",
	"state_act_Frozen": "FROZEN",
	"state_act_Release": "Release",
	"state_act_Released": "Released",
	"state_act_Obsolete": "Obsolete",
	"view_evolution_current": "Current",
	"view_evolution_projected": "Projected",
	"copy_title_to_arch_no" : "LogicalRefCopyArchitectureNumberToTitle",
	"user_pref_cues": "Convergence_Cues_Picked",
	"user_pref_openedItems_conf": "opened_items_conf_settings",
	"user_pref_workunder": "work_under_context",
	"workUnder_pos_freeValue": "work_under_position_freeValue",
	"workUnder_change": "CHANGE",
	"workUnder_evolution": "EVOLUTION",
	"cues_with_actions": ["ENOXSolutionsCueNoSolution", "ENOXSpaceAssignmentsCueNoAssignment", "ENOXSpaceAssignmentsCueMultipleAssignments"],
	"clickable_cue_icons": ["group", "alert", "attention", "status-ko", "info"],
	"limit_usrPref_openedItems_conf": 2000,
	"index_services": {
		"select_bo": ["physicalid", "logicalid", "majorid", "ds6wg:plmreference.v_islastversion", "ds6w:islastrevision", "ds6w:reserved", "ds6w:reservedBy", "ds6w:identifier", "ds6w:label", "ds6w:description", "ds6w:type", "taxonomies", "ds6wg:revision", "ds6w:created", "ds6w:modified", "ds6w:status", "ds6w:responsible", "ds6wg:architectureextension.v_architecturenumber", "ds6wg:EXC_PROTECTION_EXISTS"],
		"select_rel": ["physicalid", "ds6w:label", "ds6w:description", "ds6w:type", "taxonomies","ro.plminstance.v_effectivitycompiledform", "ds6w:modified"],
		"select_img": ["thumbnail_2d", "icon"]
	},
	"param_subtype_key": "logicalReferenceCreateShowSubTypes"
}
