{
  "columns": {
    "instanceName": "인스턴스 이름",
    "instanceMatrix": "위치 매트릭스",
    "selection": "선택",
    "ds6w:reserved": "상태 잠금",
    "ds6w:reservedBy": "잠금 소유자",
    "hide_show": "숨기기/표시",
    "find_in_ctx": "컨텍스트에서 찾기",
    "tree": "제목",
    "ds6wg:revision": "리비전",
    "ds6w:type": "유형",
    "ds6w:responsible": "담당",
    "ds6w:description": "설명",
    "ds6w:created": "타임스탬프 생성됨",
    "ds6w:modified": "수정일 타임스탬프",
    "ds6w:identifier": "식별자",
    "thumbnail": "섬네일",
    "ds6w:policy": "협업 정책",
    "ds6w:organizationResponsible": "조직",
    "ds6w:project": "협업 공간",
    "isDuplicated": "중복됨",
    "isLastMinorRevision": "최근 리비전 없음",
    "svg": "미리보기"
  },
  "tooltip_reserved": "잠김",
  "tooltip_unreserved": "잠금 해제됨",
  "tooltip_thumbnail": "섬네일을 보려면 클릭",
  "tooltip_true": "참",
  "tooltip_false": "거짓",
  "exportMask": "CSV 내보내기.",
  "customize_title": "트리 목록 보기 사용자 정의",
  "PrintOptions_title": "인쇄할 열 선택",
  "PrintOptions_header": "인쇄할 열",
  "PrintOptions_ok": "인쇄",
  "ExportCSVOptions_title": "내보낼 열 선택",
  "ExportCSVOptions_header": "내보낼 열",
  "ExportCSVOptions_ok": "내보내기",
  "reset": "재설정",
  "ColumnVisibility_title": "표시할 열 선택",
  "ColumnVisibility_header": "열 이름",
  "ColumnVisibility_color": "색상",
  "ColumnVisibility_ok": "확인",
  "ColumnVisibility_cancel": "템플릿으로 저장",
  "treelistview_customization_selection": "대화 상자",
  "treelistview_customization_hide_show": "3D에서 숨기기/표시",
  "treelistview_customization_find_in_ctx": "컨텍스트에서 찾기",
  "treelistview_customization_instanceName": "인스턴스 이름",
  "treelistview_customization_instanceMatrix": "위치 매트릭스",
  "treelistview_customization_thumbnail": "섬네일 표시",
  "treelistview_customization_svg": "미리보기",
  "padcustomizeview_ColumnVisibility_title": "열 사용자 정의",
  "padcustomizeview_PrintOptions_title": "인쇄 옵션",
  "padcustomizeview_ExportCSVOptions_title": "내보내기 옵션",
  "padcustomizeview_ColumnVisibility_instruction": "대화 상자를 선택하여 열을 숨기거나 표시할 수 있습니다.",
  "padcustomizeview_PrintOptions_instruction": "대화 상자를 선택하여 인쇄할 열을 선택합니다.",
  "padcustomizeview_ExportCSVOptions_instruction": "대화 상자를 선택하여 내보낼 열을 선택합니다.",
  "padcustomizeview_button_reset": "재설정",
  "padcustomizeview_button_close": "닫기",
  "padcustomizeview_button_save": "저장",
  "padcustomizeview_button_cancel": "취소",
  "padcustomizeview_column_name_header": "열 이름",
  "padcustomizeview_color_header": "색상",
  "padcustomizeview_apply_to_this_app": "이 앱에만 옵션 적용",
  "padcustomizeview_tooltip_show_or_hide": "이 열 표시/숨기기",
  "padcustomizeview_tooltip_cannot_hide": "이 열은 숨길 수 없습니다.",
  "padcustomizeview_tooltip_set_color": "이 열의 색상 설정",
  "padcustomizeview_tooltip_apply_toggle": "다른 앱에도 변경 사항을 적용할지 제어합니다.",
  "PADColorView_content": "a",
  "density": "밀도",
  "Comfortable": "편안함",
  "ComfortableExplanation": "모바일 장치에 적합",
  "Compact": "소형",
  "CompactExplanation": "마우스 사용에 적합",
  "more": "자세히",
  "colorPicker": {
    "title": "사용자 정의 색상 추가",
    "addTitle": "추가",
    "resetTitle": "재설정",
    "OKtitle": "저장 및 적용",
    "Canceltitle": "취소",
    "Resettitle": "재설정",
    "preview": "미리보기",
    "backgroundColor": "배경 색상",
    "textColor": "텍스트 색상",
    "titleCustom": "사용자 정의 색상 추가"
  },
  "colorView": {
    "content": "a",
    "checkmark": "&#x2714;"
  },
  "PADFind_matchcase": "대소문자 일치",
  "PADFind_wholeword": "전체 단어",
  "PADFind_close": "닫기"
}