{
  "branch": "New Branch",
  "compare": "Compare",
  "compareTo": "Compare to Selected",
  "compareWithBranchOrigin": "Compare with Branch Origin",
  "displayFilter": "Display Filter",
  "deleteVersion": "Delete",
  "newRevision": "New Revision",
  "newEvolution": "Create Evolution",
  "newBranch": "Create Branch",
  "newVersion": "Create Version",
  "noActions": "No Actions",
  "open": "Open",
  "openWith": "Open With",
  "properties": "Properties",
  "relations": "Relations",
  "version": "Version"
}
