{
  "Merge": "Zusammenführen",
  "Merging": "Zusammenführen",
  "MergeStructure": "Struktur zusammenführen",
  "MergeConfirmTitle": "Zusammenführung bestätigen",
  "MergeConfirmMsg": "Die Zusammenführung durchführen?",
  "MergeSuccessMsg": "Zusammenführung erfolgreich",
  "MergeFailureMsg": "Zusammenführung nicht erfolgreich",
  "MergeConfirmCloseDialogMsg": "Möchten Sie das Zusammenführen-Dialogfeld schließen?",
  "Revise": "Überarbeiten",
  "Reuse": "Rechts wiederverwenden",
  "ReuseRef": "Links wiederverwenden",
  "Exclude": "Ausschließen",
  "InsertNew": "Neue einfügen",
  "Maturity": "Bearbeitungsstatus",
  "Result": "Ergebnis",
  "Action": "Aktion",
  "ActionFilter": "Aktionsfilter",
  "ReapplyCurrentFilter": "Den aktuellen Filter erneut anwenden",
  "ContentColorIndicator": "Farbanzeige des Inhalts",
  "ContentFromLeft": "Inhalt von links",
  "ContentFromRight": "Inhalt von rechts",
  "TreePanelCaptionReference": "Referenz",
  "TreePanelCaptionSource": "Quelle"
}