{
  "name": "名称",
  "title": "タイトル",
  "maturity": "完成度",
  "maturityState": "完成度ステート",
  "routeBasePurpose": "ルートの基本目的",
  "Approval": "承認",
  "Review": "レビュー",
  "Standard": "標準",
  "revision": "リビジョン",
  "description": "説明",
  "owner": "所有者",
  "activity_state": "アクティビティ状態",
  "tileView": "タイル ビュー",
  "gridView": "グリッド ビュー",
  "home": "ホーム",
  "filter": "フィルタ",
  "filterOwnedbyme": "自分が所有",
  "filterSharedwithme": "自分と共有",
  "filterDraft": "ドラフト",
  "filterReleased": "リリース済み",
  "filterOwnedbymeTooltip": "自分が所有するテンプレート",
  "filterSharedwithmeTooltip": "自分と共有しているテンプレート",
  "filterDraftTooltip": "ドラフト ステートのテンプレート",
  "filterReleasedTooltip": "リリース済みステートのテンプレート",
  "state_Define": "ドラフト",
  "state_Released": "リリース済み",
  "properties": "プロパティ",
  "tasks": "タスク",
  "newTemplate": "新規テンプレート",
  "release": "リリース",
  "saveAsDraft": "ドラフトとして保存",
  "cancel": "キャンセル",
  "createRouteFromTemplate": "このテンプレートからの新規ルート",
  "Information": "情報",
  "Open": "開く",
  "Delete": "削除",
  "ErrorTemplateRemoveSelection": "削除するテンプレートを 1 つ以上選択してください。",
  "removeTemplateHeaderSingle": "{count} 個のテンプレートを削除しています",
  "removeTemplateHeader": "{count} 個のテンプレートを削除しています",
  "removeTemplateWarning": "このコンテンツを削除してよろしいですか?",
  "removeTemplateWarningDetailSingle": "次のテンプレートを削除すると、<b>永続的に</b>除去されて元に戻せなくなります: ",
  "removeTemplateWarningDetail": "次のテンプレートを削除すると、<b>永続的に</b>除去されて元に戻せなくなります: ",
  "removeTemplateHeader2": "削除するテンプレートがありません",
  "removeTemplateWarningDetail2Single": "次のテンプレートは削除できません。別のテンプレートとリンクされているか、アクセス権がありません: ",
  "removeTemplateWarningDetail2": "次のテンプレートは削除できません。別のテンプレートにリンクされているか、アクセス権がありません: ",
  "ErrorTemplateReviseSelection": "改訂するテンプレートを 1 つ以上選択してください。",
  "reviseTemplateHeader": "リビジョンを新規作成 ",
  "reviseTemplateWarning": "このコンテンツを改訂してよろしいですか?",
  "reviseTemplateWarningDetailSingle": "次のテンプレートを改訂すると、<b>永続的に</b>改訂されて元に戻せなくなります: ",
  "reviseTemplateWarningDetail2Single": "次のテンプレートは改訂できません。少なくとも 1 つの作成に使用されているか、アクセス権がありません: ",
  "revisions": "リビジョン",
	"Approval": "承認",
	"Review": "レビュー",
  "standard": "標準",
  "routeCompletionAction": "ルート完了時のアクション",
	"routeBasePurpose" : "ルートの基本目的",
  "immediate": "直ちに停止",
  "deferred": "後で停止",
  "PreserveTaskOwnerSelect1": "ルートの再度開始/再開時に元のユーザーグループにリセット",
  "PreserveTaskOwnerSelect2": "ルートの再度開始/再開時に割り当てられたユーザーを保持",
  "StartRouteOnCompletion": "完了時にルートを開始",
  "searchTemplate": "テンプレートの検索",
  "autoname": "自動名称",
  "promoteConnectedObject": "関連オブジェクトをステートアップ",
  "notifyRouteOwner": "ルートオーナーに通知",
  "routeScope": "利用範囲",
  "selectScope": "利用範囲の選択",
  "scopeAll": "すべて",
  "scopeOrg": "組織",
  "routeTaskEdits": "ルート タスクの編集",
  "ModifyDeleteTaskList": "タスク リストを変更/削除",
  "ExtendTaskList": "タスク リストを拡張",
  "ModifyTaskList": "タスク リストを変更",
  "MaintainExactTaskList": "タスク リストをそのまま保持",
  "routeAutoStopOnRejection": "却下時の自動停止",
  "ChooseUsersFromUG": "ユーザー グループからユーザーを選択",
  "yes": "はい",
  "no": "いいえ",
  "PreserveTaskOwnerLabel": "ユーザー グループの割り当てを元に戻す",
  "Availability": "入手可能性",
  "availabilityUser": "ユーザー",
  "availabilityEnterprise": "エンタープライズ",
  "selectAvailabilityBookMark": "ブックマーク ルートを選択",
  "availabilityBookMark": "ブックマーク ルート",
  "infoCloseAction": "閉じる",
  "infoRelationTab": "オプション",
  "relations_tab": "関係",
  "infoHistoryTab": "履歴",
  "successCreatedAndReleased": "{tag1} が作成され、リリースされました",
  "errorNameFormat": "タイトルが長すぎます。短い値を指定してください。",
  "buttonProgress": "テンプレートを作成しています...",
  "successCreate": "{tag1} が作成されました",
  "errorCreateRouteTemplateForRoleTitle": "このタイプのオブジェクトを作成できません: テンプレート。",
  "errorCreateRouteTemplateForRoleSubTitle": "正しい資格情報を使用していることを確認してください。",
  "errorCreateRouteTemplateForRoleMsg": "このタイプのオブジェクトを作成するために必要なアクセス ロールがターゲット コラボレーション スペースにない可能性があります。",
  "routeOwnerTask": "ルート オーナーにタスクの割り当てを依頼します",
  "relatedErrorMessage": "一部の属性が編集中です。切り替えるには変更を確定するかまたはキャンセルしてください。",
  "relatedSuccessfulMesaage": "変更に成功しました",
  "editMode": "編集モード",
  "save": "保存",
  "createhistory": "テンプレートが作成されました。",
  "createhistorydes": "テンプレートが {tag1} によって作成されました。",
  "revisehistory": "テンプレートが改訂されました。",
  "revisehistorydes": "テンプレートが {tag1} によって {tag2} から改訂されました。",
  "promotehistory": "テンプレートが活動化されました。",
  "promotehistorydes": "テンプレートが {tag1} によって活動化されました。",
  "demotehistory": "テンプレートが非活動化されました。",
  "demotehistorydes": "テンプレートが {tag1} によって非活動化されました。",
  "changeownerhistory": "テンプレート オーナーが変更されました。",
  "changeownerhistorydes": "テンプレート オーナーが {tag1} によって {tag2} から {tag3} に変更されました。",
    "changeownerhistorydes":"テンプレート オーナーが {tag1} によって {tag2} から {tag3} に変更されました。",
  "successRemoveTemplateSingle": "{count} 個のテンプレートが削除されました。",
  "successRemoveTemplate": "{count} 個のテンプレートが削除されました。",
  "errorRemove": "テンプレートを除去できません。テンプレートからルートが作成されていないことを確認してください。",
  "errorModify": "変更できません",
  "newRevision": "新規リビジョン",
  "successRevise": "テンプレートが正常に改訂されました",
  "errorRevise": "テンプレートの改訂に失敗しました",
  "routeOwnerTaskAssignmentScope": "割り当て範囲",
  "linkedTemplateSelectMessage": "完了時にルートを開始の有効なテンプレートを選択してください",
  "idCardHeaderActionTemplateAction": "テンプレート アクション",
  "loadingTemplatesMessage": "テンプレートを更新しています",
  "infoRefreshError": "データの更新中にエラーが発生しました",
  "setToState": "設定先 ",
  "changeStateSuccess": "完成度は正常に変更されました",
  "changeStateError": "完成度ステートの変更に失敗しました",
  "errorRefresh": "リフレッシュに失敗しました",
  "errorRouteNameFormat": "タイトルが長すぎます。短い値を指定してください。",
  "idCardHeaderTemplateActivityState": "テンプレート状態アクション",
  "routeRequiresESign": "署名による承認",
  "placeholderDescription": "説明を入力",
  "placeholderName": "テンプレートのタイトル",
  "DemoteOnRejection": "タスクの却下時にコンテンツをステートダウン",
  "taggerWarning": "6WTagger は、最初の1000オブジェクトに対してのみロードされます"
}