{
  "resultAttrPanelTitle": " Attributi",
  "DisplayHistorySuccessfulLbl": "Cronologia visualizzazione diapositive eliminata",
  "otherParams": "Altri",
  "hiddenText": "Commento",
  "urls": "URL",
  "relatedDocs": "Documenti",
  "failureModes": "Modalità guasto",
  "navReq": "Requisiti",
  "generalToleranceName": "Nome tolleranza generale",
  "generalToleranceVariation": "Variazione tolleranza generale",
  "tabulatedLimit": "Limiti con tabulazioni",
  "toleranceLimitMin": "Tolleranza min.",
  "toleranceLimitMax": "Tolleranza max.",
  "noaText": "Testo NOA",
  "noaType": "Tipo NOA",
  "text": "Testo"
}