{
"VisuBackView.Title":"Вид сзади",
"VisuBackView.ShortHelp":"Применение стандартного вида сзади.",
"VisuBottomView.Title":"Вид снизу",
"VisuBottomView.ShortHelp":"Применение стандартного вида снизу.",
"VisuCleanSpaceEnv.Title":"Белоснежный",
"VisuCleanSpaceEnv.ShortHelp":"Применяет окружение Белоснежный.",
"VisuCleanSpaceEnv.LongHelp":"В этом окружении есть поверхность, тень и зеркальный эффект.",
"VisuDarkBlueEnv.Title":"Синий дизайн",
"VisuDarkBlueEnv.ShortHelp":"Применяет окружение Синий дизайн.",
"VisuDarkBlueEnv.LongHelp":"В этом окружении есть сетка, поверхность, небо, горизонт, но нет теней.",
"VisuDarkGreyEnv.Title":"Затемненный обзор",
"VisuDarkGreyEnv.ShortHelp":"Применяет окружение Затемненный обзор.",
"VisuDarkGreyEnv.LongHelp":"В этом окружении есть поверхность, но отсутствует зеркальный эффект.",
"VisuFilterAxis.Title":"Скрыть/показать справочные оси",
"VisuFilterAxis.ShortHelp":"Скрытие и отображение линий справочных осей.",
"VisuFilterLines.Title":"Скрыть/показать линии",
"VisuFilterLines.ShortHelp":"Скрытие или отображение линий.",
"VisuFilterPoints.Title":"Скрыть/показать точки",
"VisuFilterPoints.ShortHelp":"Скрытие или отображение точек.",
"VisuFrontView.Title":"Вид спереди",
"VisuFrontView.ShortHelp":"Применение стандартного вида спереди.",
"VisuHideShow.Title":"Скрыть/показать",
"VisuHideShow.ShortHelp":"Скрывать или показывает объект или набор объектов.",
"VisuIsoView.Title":"Изометрический вид",
"VisuIsoView.ShortHelp":"Применение стандартного изометрического вида.",
"VisuLeftView.Title":"Вид слева",
"VisuLeftView.ShortHelp":"Применение стандартного вида слева.",
"VisuMaterialMode.Title":"Режим материала",
"VisuMaterialMode.ShortHelp":"Переключение на режим материала.",
"VisuNoEnv.Title":"Базовый",
"VisuNoEnv.ShortHelp":"Применение среды визуализации по умолчанию.",
"VisuNoEnv.LongHelp":"Не определено окружение (нейтральная среда).",
"VisuNoShadingEdges.Title":"Каркас",
"VisuNoShadingEdges.ShortHelp":"Отображение только кромок и линий объекта.",
"VisuOrthographicView.Title":"Параллельный",
"VisuOrthographicView.ShortHelp":"Отображение объектов в параллельном виде.",
"VisuPanView.Title":"Панорама",
"VisuPanView.ShortHelp":"Перемещение вида модели по горизонтали и вертикали.",
"VisuPanView.LongHelp":"Нажмите Панорама и выполните перетаскивание в любом направлении.",
"VisuPerspectiveView.Title":"Перспектива",
"VisuPerspectiveView.ShortHelp":"Отображение объектов в перспективном виде.",
"VisuReframeView.Title":"Перекадрирование",
"VisuReframeView.ShortHelp":"Вписывает всю модель в графическую область.",
"VisuReframeView.LongHelp":"Одновременно увеличивается область в средстве просмотра.",
"VisuRightView.Title":"Вид справа",
"VisuRightView.ShortHelp":"Применение стандартного вида справа.",
"VisuRotateView.Title":"Повернуть",
"VisuRotateView.ShortHelp":"Поворачивает модель по вертикальной или горизонтальной оси.",
"VisuRotateView.LongHelp":"Нажмите Повернуть, затем выполните перетаскивание по горизонтали или вертикали.",
"VisuShading.Title":"Затенение",
"VisuShading.ShortHelp":"Затеняет поверхности геометрии.",
"VisuShadingIllustration.Title":"Иллюстрация",
"VisuShadingIllustration.ShortHelp":"Применение режима каркасного представления, в котором отображаются видимые кромки и контуры объектов.",
"VisuShadingEdges.Title":"Затенение с кромками",
"VisuShadingEdges.ShortHelp":"Затенение с кромками, включая сглаженные.",
"VisuShadingEdgesHiddenEdges.Title":"Затенение с кромками и скрытыми кромками",
"VisuShadingEdgesHiddenEdges.ShortHelp":"Затенение со всеми кромками, включая скрытые.",
"VisuShadingEdgesNoSmoothEdges.Title":"Затенение с кромками без сглаженных кромок",
"VisuShadingEdgesNoSmoothEdges.ShortHelp":"Затенение с кромками, за исключением сглаженных.",
"VisuShadingMaterial.Title":"Затенение c материалом",
"VisuShadingMaterial.ShortHelp":"Отображает материал, примененный к объекту.",
"VisuShadingMaterialEdges.Title":"Затенение с материалом и кромками",
"VisuShadingMaterialEdges.ShortHelp":"Отображение материала, примененного к объекту, с кромками.",
"VisuShinyEnv.Title":"Темное зеркало",
"VisuShinyEnv.ShortHelp":"Применяет окружение Темное зеркало.",
"VisuShinyEnv.LongHelp":"В этом окружении есть поверхность, тень и зеркальный эффект, а два источника света совпадают с неонами, что позволяет отбрасывать тени на поверхности.",
"VisuTopView.Title":"Вид сверху",
"VisuTopView.ShortHelp":"Применение стандартного вида сверху.",
"VisuV6Env.Title":"Белый обзор",
"VisuV6Env.ShortHelp":"Применяет окружение Белый обзор.",
"VisuV6Env.LongHelp":"В этом окружении есть поверхность, тень, но отсутствует зеркальный эффект.",
"VisuVisibleSpace.Title":"Сменить видимое пространство",
"VisuVisibleSpace.ShortHelp":"Отображение объектов, перенесенных в скрытое пространство.",
"VisuVisibleSpace.LongHelp":"Все остальные элементы не отображаются. Цвет фона меняется, чтобы определить это пространство. <p>Нажмите еще раз, чтобы вернуться к невидимому пространству. </p>",
"VisuZoomView.Title":"Увеличить или уменьшить",
"VisuZoomView.ShortHelp":"Выполните перетаскивание вверх для увеличения масштаба или вниз — для его уменьшения.",
"VisuZoomView.LongHelp":"Нажмите на значок еще раз, чтобы остановить масштабирование.",
"VisuGrid.Title":"Переключить сетку",
"VisuGrid.ShortHelp":"Отображение или скрытие сетки на поверхности.",
"VisuToggleMirror.Title":"Переключить зеркало",
"VisuToggleMirror.ShortHelp":"Отображение или скрытие отражений объектов геометрии на поверхности.",
"VisuToggleShadow.Title":"Переключить тени",
"VisuToggleShadow.ShortHelp":"Отображение или скрытие теней объектов геометрии на поверхности.",
"VisuBackViewCmd.Title":"Вид сзади",
"VisuBackViewCmd.ShortHelp":"Применение стандартного вида сзади.",
"VisuBottomViewCmd.Title":"Вид снизу",
"VisuBottomViewCmd.ShortHelp":"Применение стандартного вида снизу.",
"VisuCleanSpaceEnvCmd.Title":"Белоснежный",
"VisuCleanSpaceEnvCmd.ShortHelp":"Применяет окружение Белоснежный.",
"VisuCleanSpaceEnvCmd.LongHelp":"В этом окружении есть поверхность, тень и зеркальный эффект.",
"VisuDarkBlueEnvCmd.Title":"Синий дизайн",
"VisuDarkBlueEnvCmd.ShortHelp":"Применяет окружение Синий дизайн.",
"VisuDarkBlueEnvCmd.LongHelp":"Это окружение содержит сетку, поверхность, небо, горизонт, но не содержит теней.",
"VisuDarkGreyEnvCmd.Title":"Затемненный обзор",
"VisuDarkGreyEnvCmd.ShortHelp":"Применяет окружение Затемненный обзор.",
"VisuDarkGreyEnvCmd.LongHelp":"В этом окружении есть поверхность, но отсутствует зеркальный эффект.",
"VisuFilterAxisCmd.Title":"Скрыть/показать справочные оси",
"VisuFilterAxisCmd.ShortHelp":"Скрытие и отображение линий справочных осей.",
"VisuFilterAxisEnableCmd.Title":"Скрыть/показать справочные оси",
"VisuFilterAxisEnableCmd.ShortHelp":"Скрытие и отображение линий справочных осей.",
"VisuFilterAxisDisableCmd.Title":"Скрыть/показать справочные оси",
"VisuFilterAxisDisableCmd.ShortHelp":"Скрытие и отображение линий справочных осей.",
"VisuFilterLinesCmd.Title":"Скрыть/показать линии",
"VisuFilterLinesCmd.ShortHelp":"Скрытие или отображение линий.",
"VisuFilterLinesEnableCmd.Title":"Скрыть/показать линии",
"VisuFilterLinesEnableCmd.ShortHelp":"Скрытие или отображение линий.",
"VisuFilterLinesDisableCmd.Title":"Скрыть/показать линии",
"VisuFilterLinesDisableCmd.ShortHelp":"Скрытие или отображение линий.",
"VisuFilterPointsCmd.Title":"Скрыть/показать точки",
"VisuFilterPointsCmd.ShortHelp":"Скрытие или отображение точек.",
"VisuFilterPointsEnableCmd.Title":"Скрыть/показать точки",
"VisuFilterPointsEnableCmd.ShortHelp":"Скрытие или отображение точек.",
"VisuFilterPointsDisableCmd.Title":"Скрыть/показать точки",
"VisuFilterPointsDisableCmd.ShortHelp":"Скрытие или отображение точек.",
"VisuFrontViewCmd.Title":"Вид спереди",
"VisuFrontViewCmd.ShortHelp":"Применение стандартного вида спереди.",
"VisuHideShowCmd.Title":"Скрыть/показать",
"VisuHideShowCmd.ShortHelp":"Скрывать или показывает объект или набор объектов.",
"VisuIsoViewCmd.Title":"Изометрический вид",
"VisuIsoViewCmd.ShortHelp":"Применение стандартного изометрического вида.",
"VisuLeftViewCmd.Title":"Вид слева",
"VisuLeftViewCmd.ShortHelp":"Применение стандартного вида слева.",
"VisuMaterialModeCmd.Title":"Режим материала",
"VisuMaterialModeCmd.ShortHelp":"Переключение на режим материала.",
"VisuNoEnvCmd.Title":"Базовый",
"VisuNoEnvCmd.ShortHelp":"Применение среды визуализации по умолчанию.",
"VisuNoEnvCmd.LongHelp":"Не определено окружение (нейтральная среда).",
"VisuNoShadingEdgesCmd.Title":"Каркас",
"VisuNoShadingEdgesCmd.ShortHelp":"Отображение только кромок и линий объекта.",
"VisuOrthographicViewCmd.Title":"Параллельный",
"VisuOrthographicViewCmd.ShortHelp":"Отображение объектов в параллельном виде.",
"VisuPanViewCmd.Title":"Панорама",
"VisuPanViewCmd.ShortHelp":"Перемещение вида модели по горизонтали и вертикали.",
"VisuPanViewCmd.LongHelp":"Нажмите Панорама и выполните перетаскивание в любом направлении.",
"VisuPerspectiveViewCmd.Title":"Перспектива",
"VisuPerspectiveViewCmd.ShortHelp":"Отображение объектов в перспективном виде.",
"VisuReframeViewCmd.Title":"Перекадрирование",
"VisuReframeViewCmd.ShortHelp":"Вписывает всю модель в графическую область.",
"VisuReframeViewCmd.LongHelp":"Одновременно увеличивается область в средстве просмотра.",
"VisuRightViewCmd.Title":"Вид справа",
"VisuRightViewCmd.ShortHelp":"Применение стандартного вида справа.",
"VisuRotateViewCmd.Title":"Повернуть",
"VisuRotateViewCmd.ShortHelp":"Поворачивает модель по вертикальной или горизонтальной оси.",
"VisuRotateViewCmd.LongHelp":"Нажмите Повернуть, затем выполните перетаскивание по горизонтали или вертикали.",
"VisuShadingCmd.Title":"Затенение",
"VisuShadingCmd.ShortHelp":"Затеняет поверхности геометрии.",
"VisuShadingIllustrationCmd.Title":"Иллюстрация",
"VisuShadingIllustrationCmd.ShortHelp":"Применение режима каркасного представления, в котором отображаются видимые кромки и контуры объектов.",
"VisuShadingEdgesCmd.Title":"Затенение с кромками",
"VisuShadingEdgesCmd.ShortHelp":"Затенение с кромками, включая сглаженные.",
"VisuShadingEdgesHiddenEdgesCmd.Title":"Затенение с кромками и скрытыми кромками",
"VisuShadingEdgesHiddenEdgesCmd.ShortHelp":"Затенение со всеми кромками, включая скрытые.",
"VisuShadingEdgesNoSmoothEdgesCmd.Title":"Затенение с кромками без сглаженных кромок",
"VisuShadingEdgesNoSmoothEdgesCmd.ShortHelp":"Затенение с кромками, за исключением сглаженных.",
"VisuShadingMaterialCmd.Title":"Затенение c материалом",
"VisuShadingMaterialCmd.ShortHelp":"Отображает материал, примененный к объекту.",
"VisuShadingMaterialEdgesCmd.Title":"Затенение с материалом и кромками",
"VisuShadingMaterialEdgesCmd.ShortHelp":"Отображение материала, примененного к объекту, с кромками.",
"VisuShinyEnvCmd.Title":"Темное зеркало",
"VisuShinyEnvCmd.ShortHelp":"Применяет окружение Темное зеркало.",
"VisuShinyEnvCmd.LongHelp":"В этом окружении есть поверхность, тень и зеркальный эффект, а два источника света совпадают с неонами, что позволяет отбрасывать тени на поверхности.",
"VisuTopViewCmd.Title":"Вид сверху",
"VisuTopViewCmd.ShortHelp":"Применение стандартного вида сверху.",
"VisuV6EnvCmd.Title":"Белый обзор",
"VisuV6EnvCmd.ShortHelp":"Применяет окружение Белый обзор.",
"VisuV6EnvCmd.LongHelp":"В этом окружении есть поверхность, тень, но отсутствует зеркальный эффект.",
"VisuVisibleSpaceCmd.Title":"Сменить видимое пространство",
"VisuVisibleSpaceCmd.ShortHelp":"Отображение объектов, перенесенных в скрытое пространство.",
"VisuVisibleSpaceCmd.LongHelp":"Все остальные элементы не отображаются. Цвет фона меняется, чтобы определить это пространство. <p>Нажмите еще раз, чтобы вернуться к невидимому пространству. </p>",
"VisuZoomViewCmd.Title":"Увеличить или уменьшить",
"VisuZoomViewCmd.ShortHelp":"Выполните перетаскивание вверх для увеличения масштаба или вниз — для его уменьшения.",
"VisuZoomViewCmd.LongHelp":"Нажмите на значок еще раз, чтобы остановить масштабирование.",
"toggleVisuGridAction.Title":"Переключить сетку",
"toggleVisuGridAction.ShortHelp":"Отображение или скрытие сетки на поверхности.",
"VisuGridEnableCmd.Title":"Переключить сетку",
"VisuGridEnableCmd.ShortHelp":"Отображение или скрытие сетки на поверхности.",
"VisuGridDisableCmd.Title":"Переключить сетку",
"VisuGridDisableCmd.ShortHelp":"Отображение или скрытие сетки на поверхности.",
"toggleVisuMirrorAction.Title":"Переключить зеркало",
"toggleVisuMirrorAction.ShortHelp":"Отображение или скрытие отражений объектов геометрии на поверхности.",
"VisuMirrorEnableCmd.Title":"Переключить зеркало",
"VisuMirrorEnableCmd.ShortHelp":"Отображение или скрытие отражений объектов геометрии на поверхности.",
"VisuMirrorDisableCmd.Title":"Переключить зеркало",
"VisuMirrorDisableCmd.ShortHelp":"Отображение или скрытие отражений объектов геометрии на поверхности.",
"toggleVisuShadowAction.Title":"Переключить тени",
"toggleVisuShadowAction.ShortHelp":"Отображение или скрытие теней объектов геометрии на поверхности.",
"VisuShadowEnableCmd.Title":"Переключить тени",
"VisuShadowEnableCmd.ShortHelp":"Отображение или скрытие теней объектов геометрии на поверхности.",
"VisuShadowDisableCmd.Title":"Переключить тени",
"VisuShadowDisableCmd.ShortHelp":"Отображение или скрытие теней объектов геометрии на поверхности.",
"VisuBasicOCACmd.Title":"Базовый",
"VisuBasicOCACmd.ShortHelp":"Окружение не определено.",
"VisuBasicOCACmd.LongHelp":"Применяется нейтральная среда.",
"VisuWhiteDesignOCACmd.Title":"Белый дизайн",
"VisuWhiteDesignOCACmd.ShortHelp":"Применяет окружение Белый дизайн.",
"VisuWhiteDesignOCACmd.LongHelp":"В этом окружении есть сетка, поверхность, небо, горизонт, но нет теней.",
"VisuBlueDesignOCACmd.Title":"Синий дизайн",
"VisuBlueDesignOCACmd.ShortHelp":"Применяет окружение Синий дизайн.",
"VisuBlueDesignOCACmd.LongHelp":"В этом окружении есть сетка, поверхность, небо, горизонт, но нет теней.",
"VisuDarkDesignOCACmd.Title":"Темный дизайн",
"VisuDarkDesignOCACmd.ShortHelp":"Применяет окружение Темный дизайн.",
"VisuDarkDesignOCACmd.LongHelp":"В этом окружении есть сетка, поверхность, небо, горизонт, но нет теней.",
"VisuStudioOCACmd.Title":"Студия",
"VisuStudioOCACmd.ShortHelp":"Применяет окружение Студия.",
"VisuStudioOCACmd.LongHelp":"В этом окружении есть поверхность, тень и зеркальный эффект. <p audience = 'nodoc'>Оно очень похоже на окружение <uicontrol>Белое зеркало</uicontrol>. Основные различия заключаются в карте отражения, более адаптированной к обзору, и двух источниках света, освещающих сцену (первый имеет теплый свет, а второй — холодный).</p>",
"VisuPureWhiteOCACmd.Title":"Белоснежный",
"VisuPureWhiteOCACmd.ShortHelp":"Применяет окружение Белоснежный.",
"VisuPureWhiteOCACmd.LongHelp":"В этом окружении есть поверхность, тень и зеркальный эффект. Это окружение по умолчанию.",
"VisuWhiteMirrorOCACmd.Title":"Белое зеркало",
"VisuWhiteMirrorOCACmd.ShortHelp":"Применяет окружение Белое зеркало.",
"VisuWhiteMirrorOCACmd.LongHelp":"В этом окружении есть белая поверхность, тень и зеркальный эффект.",
"VisuWhiteReviewOCACmd.Title":"Белый обзор",
"VisuWhiteReviewOCACmd.ShortHelp":"Применяет окружение Белый обзор.",
"VisuWhiteReviewOCACmd.LongHelp":"В этом окружении есть поверхность, тень, но отсутствует зеркальный эффект.",
"VisuDarkMirrorOCACmd.Title":"Темное зеркало",
"VisuDarkMirrorOCACmd.ShortHelp":"Применяет окружение Темное зеркало.",
"VisuDarkMirrorOCACmd.LongHelp":"В этом окружении есть поверхность, тень и зеркальный эффект, а два источника света совпадают с неонами, что позволяет отбрасывать тени на поверхности.",
"VisuDarkReviewOCACmd.Title":"Затемненный обзор",
"VisuDarkReviewOCACmd.ShortHelp":"Применяет окружение Затемненный обзор.",
"VisuDarkReviewOCACmd.LongHelp":"В этом окружении есть поверхность, но отсутствует зеркальный эффект.",
"VisuOutdoorOCACmd.Title":"Внешняя среда",
"VisuOutdoorOCACmd.ShortHelp":"Применяет окружение Внешняя среда.",
"VisuOutdoorOCACmd.LongHelp":"В этом окружении есть небо, поверхность и тени между объектами.<p audience = 'nodoc'>Для окружений Обзор используется технология освещения SSAO.</p>",
"VisuIndoorOCACmd.Title":"В помещении",
"VisuIndoorOCACmd.ShortHelp":"Применяет окружение В помещении.",
"VisuIndoorOCACmd.LongHelp":"В этом окружении есть поверхность, тень, три источника света и размытый зеркальный эффект.",
"VisuCityOCACmd.Title":"Город",
"VisuCityOCACmd.ShortHelp":"Применяет окружение Город.",
"VisuCityOCACmd.LongHelp":"В этом окружении есть один источник света, наземная тень и тени между объектами.",
"VisuWhiteExperienceOCACmd.Title":"Светлые возможности",
"VisuWhiteExperienceOCACmd.ShortHelp":"Применяет окружение Светлые возможности. Это значение используется по умолчанию.",
"VisuWhiteExperienceOCACmd.LongHelp":"В этом окружении есть поверхность, тень и зеркальный эффект. В нем также есть фон (с прохладной областью, теплой областью и 2 неоновыми лампами).<p audience = 'nodoc'>IBL (освещение на основе изображения) активируется с результатом, аналогичным фону, но с большей детализацией и контрастом.</p>",
"VisuRoadOCACmd.Title":"Дорога",
"VisuRoadOCACmd.ShortHelp":"Применяет окружение Дорога.",
"VisuRoadOCACmd.LongHelp":"В этом окружении есть один источник света, наземная тень и тени между объектами.",
"VisuQMCommand.Title":"Качество изображения",
"VisuQMCommand.ShortHelp":"Позволяет изменить производительность отрисовки и качество визуализации.",
"VisuQMCommand.LongHelp":"Можно использовать предустановки или настроить некоторые параметры визуализации с помощью специального редактора.",
"VisuViewPanelCommand.Title":"Режимы просмотра",
"VisuViewPanelCommand.ShortHelp":"Позволяет изменять текущий вид с помощью предварительно заданных режимов вида.",
"VisuViewPanelCommand.LongHelp":"Можно также применить к объектам стандартные или предопределенные внешние виды и изменить текущее окружение.",
"VisuPageObjectsConsoleCommand.Title":"Консоль объектов страницы визуализации",
"VisuPageObjectsConsoleCommand.ShortHelp":"Открытие редактора визуализации.",
"VisuCleanSpaceEnv.WebHelp":"SharedUserMap/shared-services-r-Widget-BasicViewingCommands.htm#shared-services-r-Widget-BasicViewingCommands",
"VisuDarkBlueEnv.WebHelp":"SharedUserMap/shared-services-r-Widget-BasicViewingCommands.htm#shared-services-r-Widget-BasicViewingCommands",
"VisuDarkGreyEnv.WebHelp":"SharedUserMap/shared-services-r-Widget-BasicViewingCommands.htm#shared-services-r-Widget-BasicViewingCommands",
"VisuNoEnv.WebHelp":"SharedUserMap/shared-services-r-Widget-BasicViewingCommands.htm#shared-services-r-Widget-BasicViewingCommands",
"VisuShadingIllustration.WebHelp":"SharedUserMap/shared-services-r-Widget-BasicViewingCommands.htm#shared-services-r-Widget-BasicViewingCommands",
"VisuShinyEnv.WebHelp":"SharedUserMap/shared-services-r-Widget-BasicViewingCommands.htm#shared-services-r-Widget-BasicViewingCommands",
"VisuV6Env.WebHelp":"SharedUserMap/shared-services-r-Widget-BasicViewingCommands.htm#shared-services-r-Widget-BasicViewingCommands",
"VisuCleanSpaceEnvCmd.WebHelp":"SharedUserMap/shared-services-r-Widget-BasicViewingCommands.htm#shared-services-r-Widget-BasicViewingCommands",
"VisuDarkBlueEnvCmd.WebHelp":"SharedUserMap/shared-services-r-Widget-BasicViewingCommands.htm#shared-services-r-Widget-BasicViewingCommands",
"VisuDarkGreyEnvCmd.WebHelp":"SharedUserMap/shared-services-r-Widget-BasicViewingCommands.htm#shared-services-r-Widget-BasicViewingCommands",
"VisuNoEnvCmd.WebHelp":"SharedUserMap/shared-services-r-Widget-BasicViewingCommands.htm#shared-services-r-Widget-BasicViewingCommands",
"VisuShadingIllustrationCmd.WebHelp":"SharedUserMap/shared-services-r-Widget-BasicViewingCommands.htm#shared-services-r-Widget-BasicViewingCommands",
"VisuShinyEnvCmd.WebHelp":"SharedUserMap/shared-services-r-Widget-BasicViewingCommands.htm#shared-services-r-Widget-BasicViewingCommands",
"VisuV6EnvCmd.WebHelp":"SharedUserMap/shared-services-r-Widget-BasicViewingCommands.htm#shared-services-r-Widget-BasicViewingCommands",
"VisuBasicOCACmd.WebHelp":"SharedUserMap/shared-services-r-Widget-BasicViewingCommands.htm#shared-services-r-Widget-BasicViewingCommands",
"VisuWhiteDesignOCACmd.WebHelp":"SharedUserMap/shared-services-r-Widget-BasicViewingCommands.htm#shared-services-r-Widget-BasicViewingCommands",
"VisuBlueDesignOCACmd.WebHelp":"SharedUserMap/shared-services-r-Widget-BasicViewingCommands.htm#shared-services-r-Widget-BasicViewingCommands",
"VisuDarkDesignOCACmd.WebHelp":"SharedUserMap/shared-services-r-Widget-BasicViewingCommands.htm#shared-services-r-Widget-BasicViewingCommands",
"VisuStudioOCACmd.WebHelp":"SharedUserMap/shared-services-r-Widget-BasicViewingCommands.htm#shared-services-r-Widget-BasicViewingCommands",
"VisuPureWhiteOCACmd.WebHelp":"SharedUserMap/shared-services-r-Widget-BasicViewingCommands.htm#shared-services-r-Widget-BasicViewingCommands",
"VisuWhiteMirrorOCACmd.WebHelp":"SharedUserMap/shared-services-r-Widget-BasicViewingCommands.htm#shared-services-r-Widget-BasicViewingCommands",
"VisuWhiteReviewOCACmd.WebHelp":"SharedUserMap/shared-services-r-Widget-BasicViewingCommands.htm#shared-services-r-Widget-BasicViewingCommands",
"VisuDarkMirrorOCACmd.WebHelp":"SharedUserMap/shared-services-r-Widget-BasicViewingCommands.htm#shared-services-r-Widget-BasicViewingCommands",
"VisuDarkReviewOCACmd.WebHelp":"SharedUserMap/shared-services-r-Widget-BasicViewingCommands.htm#shared-services-r-Widget-BasicViewingCommands",
"VisuOutdoorOCACmd.WebHelp":"SharedUserMap/shared-services-r-Widget-BasicViewingCommands.htm#shared-services-r-Widget-BasicViewingCommands",
"VisuIndoorOCACmd.WebHelp":"SharedUserMap/shared-services-r-Widget-BasicViewingCommands.htm#shared-services-r-Widget-BasicViewingCommands",
"VisuCityOCACmd.WebHelp":"SharedUserMap/shared-services-r-Widget-BasicViewingCommands.htm#shared-services-r-Widget-BasicViewingCommands",
"VisuWhiteExperienceOCACmd.WebHelp":"SharedUserMap/shared-services-r-Widget-BasicViewingCommands.htm#shared-services-r-Widget-BasicViewingCommands",
"VisuRoadOCACmd.WebHelp":"SharedUserMap/shared-services-r-Widget-BasicViewingCommands.htm#shared-services-r-Widget-BasicViewingCommands",
"VisuQMCommand.WebHelp":"SharedUserMap/com-t-View-WebQualityManager.htm#com-t-View-WebQualityManager",
"VisuQMCommand.PanelHelp":"SharedUAPanelMap/shared-services-uapanel-t-QualityManager.htm#shared-services-uapanel-t-QualityManager.xml",
"VisuViewPanelCommand.WebHelp":"SharedUserMap/shared-services-t-ViewModes.htm#shared-services-t-ViewModes",
"VisuViewPanelCommand.PanelHelp":"SharedUAPanelMap/shared-services-t-ViewModes.htm#shared-services-t-ViewModes"
}
