{
  "cancel": "Abbrechen",
  "Invite": "Einladen",
  "send": "Senden",
  "descriptionField": "Einladung",
  "textByDefaultInvitation": "möchte Sie seinem/ihrem Netzwerk hinzufügen",
  "SendAndInvitationto": "Einladung senden an",
  "addSuccess": "Ihre Einladung wurde erfolgreich gesendet",
  "Message": "Nachricht",
  "Pleasefillthefieldscorrectly": "Felder korrekt ausfüllen",
  "invitationsSent": "Ihre Einladungen wurde gesendet.",
  "alreadyInNetwork": "Die eingeladenen Personen sind bereits in Ihrem Netzwerk oder haben Einladungen erhalten"
}