{
"CAT3DAnnotationLevelSelectorHdr.Title":"Sélecteur de niveau",
"CAT3DAnnotationLevelSelectorHdr.ShortHelp":"Affichez le sélecteur de niveau.",
"CAT3DAnnotationHideHdr.Title":"Hide",
"CAT3DAnnotationHideHdr.ShortHelp":"Cachez les annotations sélectionnées ou les annotations associées à l'objet sélectionné.",
"CAT3DAnnotationShowHdr.Title":"Afficher",
"CAT3DAnnotationShowHdr.ShortHelp":"Affichez les annotations sélectionnées ou les annotations associées à l'objet sélectionné.",
"CAT3DAnnotationSetHideHdr.Title":"Cacher l'ensemble d'annotations",
"CAT3DAnnotationSetHideHdr.ShortHelp":"Cachez l'ensemble d'annotations.",
"CAT3DAnnotationSetShowHdr.Title":"Afficher l'ensemble d'annotations",
"CAT3DAnnotationSetShowHdr.ShortHelp":"Affichez l'ensemble d'annotations sélectionné.",
"CAT3DAnnotationBrowserHdr.Title":"Annotations 3D",
"CAT3DAnnotationBrowserHdr.ShortHelp":"Affiche les miniatures des vues et des captures dans le panneau <wintitle>Vues et captures</wintitle>.",
"CAT3DAnnotationBrowserHdr.LongHelp":"Sélectionnez la miniature d'une vue ou d'une capture pour l'activer.",
"CAT3DAnnotationSwitchOnOffHdr.Title":"Afficher les ensembles d'annotations",
"CAT3DAnnotationSwitchOnOffHdr.ShortHelp":"Affiche les ensembles d'annotations.",
"CAT3DAnnotationBlankingHdr.Title":"Espacement des annotations",
"CAT3DAnnotationBlankingHdr.ShortHelp":"Applique un espacement aux annotations lorsque le mode d'espacement sélectionné est 'Zone hachurée' ou 'Zone hachurée avec géométrie'",
"CAT3DAnnotShowAttrRelatedInfosHdr.Title":"Afficher des informations supplémentaires sur les fonctions",
"CAT3DAnnotShowAttrRelatedInfosHdr.ShortHelp":"Affichez les informations supplémentaires des fonctions sélectionnées.",
"CAT3DAnnotationBrowserHdr.WebHelp.CATA3I_AP":"A3iUserMap/a3i-t-Browser.htm",
"CAT3DAnnotationBlankingHdr.WebHelp.CATA3I_AP":"A3iUserMap/a3i-t-AnnotationBlanking.htm"
}
