{
  "DateCriteriaTitle": "Enable Date Criteria",
  "UnitCriteriaTitle": "Enable Unit Criteria",
  "SelectAFile": "Select a file...",
  "BrowseButtonText": "Browse",
  "UploadButtonText": "Upload",
  "NoFileToUpload": "Nothing to upload, select a file or use default",
  "XSLFileError": "Xsl version should be 1.0, modify file or use default",
  "DowloadCustoButton": "Current XSL",
  "DowloadDefaultButton": "Default XSL",
  "UnitSetAlertMessage": "Unit successfully set",
  "UnitUnsetAlertMessage": "Unit successfully unset",
  "DateSetAlertMessage": "Date successfully set",
  "DateUnsetAlertMessage": "Date successfully unset",
  "ProcessError": "Error during process, try again later",
  "XSLUploadSuccessAlert": "File successfully uploaded",
  "XSLAccordeonTab": "Configuration Expression Display",
  "ConfigurationCriteriaAccordeonTab": "Configuration Criteria",
  "DateDescription": "When checked, the Date criteria will be enabled",
  "UnitDescription": "When checked, the Unit criteria will be enabled",
  "ConfigurationManagementHeader": "Defines parameterization for Configured Structure",
  "SuccessfulSettingsApplied": "Setting(s) Successfully Applied.",
  "ConfigurationFilteringAccordeonTab": "Configuration Filtering",
  "StaticMappingTitle": "Enable Product Configuration instantiation",
  "StaticMappingDescription": "When checked, Product Configuration instantiation will be enabled when authoring and interpreted when exploring the structure",
  "CompositionMatrixTitle": "Enable Composition Matrix ",
  "CompositionMatrixDescription": "When checked, the Composition Matrix will be enabled and interpreted when filtering the structure"
}
