{
  "languageInformation_title": "Informazioni lingua",
  "criteria_title": "Criteri",
  "criteria_description": "una descrizione dei criteri",
  "sample_VariantClassSample1": "Colore",
  "sample_Variant1Sample": "Blu",
  "sample_Variant1Sample2": "Verde",
  "sample_VariantClassSample2": "Città",
  "sample_Variant2Sample1": "Parigi",
  "sample_Variant2Sample2": "Londra",
  "sample_VariantClassSample3": "Cittadinanza",
  "sample_Variant3Sample1": "Francese",
  "sample_VariantClassSample4": "Paese",
  "sample_Variant3Sample4": "Francia",
  "sample_OptionSample": "Scheda Wi-Fi",
  "sample_PackSample": "Sport Pack",
  "standard_operators_title": "Operatori standard",
  "standard_operators_description": "Descrizione operatori standard NLS",
  "standard_operators_not": "NOT",
  "standard_operators_and": "AND",
  "standard_operators_or": "OR",
  "standard_operators_parenthesis": "Parentesi",
  "conditional_requirement_title": "Requisito condizionale",
  "conditional_requirement_description": "Descrizione requisito condizionale",
  "conditional_requirement_imply": "IMPLY",
  "co_dependency_title": "Dichiarazione di codipendenza",
  "co_dependency_description": "Descrizione di codipendenza",
  "co_dependency_equivalent": "EQUIVALENTE",
  "incompatibility_title": "Dichiarazione incompatibile",
  "incompatibility_description": "A e B sono incompatibili equivale a",
  "criteria_Feature": "Funzione",
  "criteria_option": "Opzione",
  "criteria_severalOptions": "Varie opzioni",
  "criteria_Pack": "Pacchetto",
  "criteria_variantClass": "Classe varianti",
  "criteria_variant": "variante",
  "criteria_value": "valore",
  "criteria_values": "valori",
  "criteria_variants": "varianti",
  "criteria_severalOptions_explanation": "Una funzione seguita da un elenco di opzioni è equivalente a un operatore OR tra tutte le opzioni elencate",
  "criteria_variantclassvariants_explanation": "Una classe di variante seguita da un elenco di varianti equivale a un OR tra tutte le varianti elencate",
  "criteria_variantvalues_explanation": "Una variante seguita da un elenco di valori è equivalente a un operatore OR tra tutti i valori elencati",
  "example": "esempio",
  "criteria_featureoption_explanation": "Una funzione con un'opzione è un'espressione valida",
  "criteria_variantclassvariant_explanation": "Una classe di varianti con una variante è un'espressione valida",
  "criteria_variantvalue_explanation": "Una variante con uno dei suoi valori è un'espressione valida",
  "criteria_feature_explanation": "Una funzione senza opzioni fa riferimento a tutte le opzioni associate a questa funzione",
  "criteria_variantClass_explanation": "Una classe di varianti senza varianti fa riferimento a tutte le varianti associate a questa classe di varianti",
  "criteria_variant_explanation": "Una variante senza alcun valore si riferisce a tutti i valori associati a questa variante",
  "expression1": "espressione1",
  "expression2": "espressione2",
  "not_explanation": "Un'espressione preceduta da NOT è il componente logico dell'espressione",
  "and_explanation": "AND posto tra due espressioni esprime la congiunzione logica tra di esse",
  "or_explanation": "OR tra due espressioni esprime la disgiunzione logica tra le due",
  "parenthesis_explanation": "L'utente può creare un'espressione più complessa tramite le parentesi",
  "imply_explanation": "Un requisito condizionale - se (espressione 1), allora (espressione 2) - utilizza l'operatore IMPLY",
  "equivalent_explanation": "Equivalente fa sì che l'espressione 1 e l'espressione 2 abbiano lo stesso contenuto logico",
  "incompatibility_explanation": "L'utente potrebbe voler creare due dichiarazioni incompatibili. È possibile farlo tramite operatori esistenti",
  "option_explanation": "Un'opzione può essere utilizzata come criterio",
  "pack_explanation": "Un pacchetto può essere utilizzato come criterio"
}