{
  "ENOTRMAppDropInvit_Drop": "Hier ablegen",
  "ENOTRMApp_InsertZone": "Objekt hier einfügen",
  "ENOTRMApp_SubscribeToTRA": "Auswahlereignisse der Rückverfolgbarkeit des Systems abonnieren",
  "ENOTRMApp_Tooltip_KeyboardShortcuts": "Wussten Sie, dass Sie Tastenkombinationen zum Erstellen von Objekten verwenden können?",
  "ENOTRMApp_Tooltip_InsertReqAsChild": "ALT+I: eine Voraussetzung als Unterelement einfügen",
  "ENOTRMApp_Tooltip_InsertReqAsSibling": "ALT+G: eine Voraussetzung als erstes gleichgeordnetes Element einfügen",
  "ENOTRMApp_Tooltip_InsertChapAsChild": "ALT+J: ein Kapitel als Unterelement einfügen",
  "ENOTRMApp_Tooltip_InsertChapAsSibling": "ALT+K: ein Kapitel als erstes gleichgeordnetes Element einfügen",
  "ENOTRMApp_Tooltip_InsertFirstObject": "Fügen Sie Ihr erstes Objekt hier ein oder legen Sie es hier ab",
  "ENOTRMApp_Tooltip_DropAbove": "Oben ablegen",
  "ENOTRMApp_Tooltip_DropBelow": "Unten ablegen",
  "ENOTRMApp_Tooltip_DropAsChild": "Als Unterelement ablegen",
  "ENOTRMApp_Tooltip_NoObjects": "Keine anzuzeigenden Objekte. Fügen Sie Objekte ein.",
  "ENOTRMApp_Tooltip_CleanSelection": "Auswahl löschen",
  "ENOTRMApp_Headers_WidgetTitle": "Rich View von",
  "ENOTRMApp_Headers_Navigation": "Navigation",
  "ENOTRMApp_Headers_TipsAndTricks": "Tipps und Tricks",
  "ENOTRMApp_Headers_InsertExisting": "Vorhandenes einfügen...",
  "ENOTRMApp_Headers_Containers": "Behälter: ",
  "ENOTRMApp_Headers_Objects": "Objekte: ",
  "ENOTRMApp_Headers_Selected": "Ausgewählt: ",
  "ENOTRMApp_Headers_Status": "Status > ",
  "ENOTRMApp_Headers_TraceabilityScope": "Rückverfolgbarkeitsbereich: ",
  "ENOTRMApp_DefaultValue_None": "Keine",
  "ENOTRMApp_Notif_NotAuthorized": "Diese Operation wird für dieses Objekt nicht unterstützt",
  "ENOTRMApp_Notif_ObjectInserted": "Objekt <strong>{TNR}</strong> wurde ordnungsgemäß eingefügt",
  "ENOTRMApp_Notif_ObjectUpdated": "Objekt <strong>{TNR}</strong> wurde ordnungsgemäß aktualisiert",
  "ENOTRMApp_Notif_ObjectCreated": "Objekt <strong>{TNR}</strong> wurde ordnungsgemäß erzeugt",
  "ENOTRMApp_Notif_ObjectSaved": "Objekt <strong>{TNR}</strong> wurde ordnungsgemäß gespeichert",
  "ENOTRMApp_Notif_FatalError": "<strong>Schwerwiegender Fehler</strong>.",
  "ENOTRMApp_Notif_StructureLoaded": "Die Struktur wurde <strong>geladen</strong>.",
  "ENOTRMApp_Notif_OperationSucceeded": "Operation <strong>erfolgreich</strong>.",
  "ENOTRMApp_Notif_FailureAndRollback": "Operation <strong>fehlgeschlagen</strong>. Die Daten wurden zurückgesetzt. Versuchen Sie es erneut.",
  "ENOTRMApp_Notif_OneSearchFailure": "One Search ist nicht verfügbar",
  "ENOTRMApp_Notif_EmptyTitle": "Der Titel ist obligatorisch und darf nicht leer sein. Die Änderung wurde abgebrochen",
  "ENOTRMApp_Notif_LoadError": "Objekt konnte nicht auf dem Server gefunden werden",
  "ENOTRMApp_Cmd_StartLink": "Verknüpfung beginnen",
  "ENOTRMApp_Cmd_EndLink": "Verknüpfung beenden",
  "ENOTRMApp_Cmd_History": "Verlauf",
  "ENOTRMApp_Cmd_DeleteLink": "Verknüpfungsverwaltung",
  "ENOTRMApp_Cmd_Detach": "Entfernen",
  "ENOTRMApp_Cmd_Properties": "Eigenschaften",
  "DeleteLinkAction_ToHeader": "Liste der Objekte, die {TNR} verfeinern",
  "DeleteLinkAction_FromHeader": "Liste der durch {TNR} abgedeckten Objekte",
  "DeleteLinkAction_DeleteLinks": "Verknüpfungsverwaltung",
  "DeleteLinkAction_Delete": "Entfernen",
  "DeleteLinkAction_Cancel": "Schließen",
  "DeleteLinkAction_Success": "Verknüpfung(en) erfolgreich gelöscht",
  "DeleteLinkAction_NoLinkFound": "Keine Verknüpfungen gefunden",
  "InsertRequirement": "Neue Voraussetzung einfügen",
  "CreateRequirmentSpecification": "Anforderungsspezifikation",
  "CreateSpecificationFolder": "Spezifikationsordner",
  "AddNewRequirement": "Voraussetzung",
  "InsertComment": "Neuen Kommentar einfügen",
  "InsertChapter": "Neues Kapitel einfügen",
  "InsertExisting": "Vorhandenes Objekt einfügen",
  "InsertExistingRequirement": "Vorhandene Voraussetzung einfügen",
  "AddRequirement": "Neue Anforderung anfügen",
  "AddComment": "Neuen Kommentar anfügen",
  "AddChapter": "Neues Kapitel anfügen",
  "ExternalSubReq": "Unteranforderung",
  "InsertExistExtReq": "Vorhandene externe Anforderung einfügen",
  "ExternalDerivedReq": "Nachgelagerte Anforderung",
  "InsertNewExtReq": "Neue externe Anforderung einfügen",
  "ExternalObject_DisplayContent": "Dies ist eine Anforderung aus einem externen System. Klicken Sie, um seinen Inhalt abzurufen.",
  "ExternalObject_LoadingContent": "Inhalt wird geladen...",
  "ExternalObject_LoadingError": "Inhalt der externen Anforderung konnte nicht abgerufen werden.",
  "TRM_OptimizationLoading": "Optimiertes Laden...",
  "AddRevised_DuplicatedRootObject": "Überarbeitetes und dupliziertes Objekt automatisch als Root hinzufügen"
}